formance_sdk_python/__init__.py
formance_sdk_python/_hooks/__init__.py
formance_sdk_python/_hooks/clientcredentials.py
formance_sdk_python/_hooks/registration.py
formance_sdk_python/_hooks/sdkhooks.py
formance_sdk_python/_hooks/types.py
formance_sdk_python/_version.py
formance_sdk_python/auth.py
formance_sdk_python/auth_v1.py
formance_sdk_python/basesdk.py
formance_sdk_python/httpclient.py
formance_sdk_python/ledger.py
formance_sdk_python/ledger_v1.py
formance_sdk_python/ledger_v2.py
formance_sdk_python/models/__init__.py
formance_sdk_python/models/errors/__init__.py
formance_sdk_python/models/errors/error.py
formance_sdk_python/models/errors/errorresponse.py
formance_sdk_python/models/errors/no_response_error.py
formance_sdk_python/models/errors/paymentserrorresponse.py
formance_sdk_python/models/errors/reconciliationerrorresponse.py
formance_sdk_python/models/errors/responsevalidationerror.py
formance_sdk_python/models/errors/sdkbaseerror.py
formance_sdk_python/models/errors/sdkerror.py
formance_sdk_python/models/errors/v2error.py
formance_sdk_python/models/errors/v2errorresponse.py
formance_sdk_python/models/errors/v3errorresponse.py
formance_sdk_python/models/errors/walletserrorresponse.py
formance_sdk_python/models/errors/webhookserrorresponse.py
formance_sdk_python/models/operations/__init__.py
formance_sdk_python/models/operations/activateconfig.py
formance_sdk_python/models/operations/addaccounttopool.py
formance_sdk_python/models/operations/addmetadataontransaction.py
formance_sdk_python/models/operations/addmetadatatoaccount.py
formance_sdk_python/models/operations/cancelevent.py
formance_sdk_python/models/operations/changeconfigsecret.py
formance_sdk_python/models/operations/confirmhold.py
formance_sdk_python/models/operations/connectorstransfer.py
formance_sdk_python/models/operations/countaccounts.py
formance_sdk_python/models/operations/counttransactions.py
formance_sdk_python/models/operations/createaccount.py
formance_sdk_python-6.4.0.dist-info/METADATA
formance_sdk_python-6.4.0.dist-info/WHEEL
formance_sdk_python-6.4.0.dist-info/licenses/LICENSE
formance_sdk_python-6.4.0.dist-info/RECORD
